gradienter/__init__.py
gradienter-0.16.dist-info/METADATA
gradienter-0.16.dist-info/WHEEL
gradienter-0.16.dist-info/top_level.txt
gradienter-0.16.dist-info/RECORD
