Metadata-Version: 2.1
Name: gradienter
Version: 0.16
Summary: A package for gradients
Home-page: https://github.com/ImsilverDev/gradienter
Author: silvdev
Author-email: vadimjohn82@gmail.com
License: UNKNOWN
Platform: UNKNOWN
